{
    "day": 4,
    "topic": "In Case",
    "sections": [
      {
        "title": "Introduction",
        "content": "Welcome to Unit 114 of our English learning journey. In this unit, we'll explore the usage of 'in case' to express precaution, preparation, or the possibility of a future event. "
      },
      {
        "title": "Definition",
        "content": "Understanding how to use this expression will enhance your ability to communicate intentions and actions. Let's delve into the key concepts."
      },
      {
        "title": "Introduction to 'In Case'",
        "content": "Define the usage of 'in case' to indicate a precautionary measure or preparation for a possible future event",
        "points": [
          "Take an umbrella with you in case it rains.",
          "I'll bring some snacks in case we get hungry."
        ]
      },
      {
        "title": "Preposition 'In'",
        "content": "Discuss the role of the preposition 'in' in the expression and its connection to time or circumstances.",
        "points": [
          "We should leave early in case there's traffic",
          "I'll write down the address in case I forget."
        ]
      },
      {
        "title": "Examples",
        "content": "Let's examine examples to illustrate the application of 'in case'",
        "points": [
            "Bring your charger in case your phone battery runs out",
            "I'll pack an extra jacket in case it gets cold",
            "She carries a first aid kit in case of emergencies"
        ]
      },
      {
        "title": "Usage and Content",
        "content": "Understand the appropriate contexts for using 'in case' and how it contributes to the overall meaning of a sentence."
      },
      {
        "title": "Recap and Summary:",
        "content": "In summary, mastering the use of 'in case' allows you to express foresight and preparedness in various situations."
      },
      {
        "title": "Additional Resources:",
        "content": "For additional practice and reinforcement, consider exploring examples in language learning books and online exercises."
      },
      {
        "title": "Conclusion",
        "content": "Thank you for joining today's lesson on 'In Case.' Practice using this expression confidently in various situations, and feel free to reach out if you have any questions. Happy learning!"
      }
    ]
  }